<package>
  <description brief="filter_cloud_color">

     filter_cloud_color

  </description>
  <author>Sibi Venkatesan</author>
  <license>BSD</license>
  <review status="unreviewed" notes=""/>
  <url>http://ros.org/wiki/filter_cloud_color</url>
  <depend package="roscpp"/>
  <depend package="rospy"/>
  <depend package="tf"/>
  <depend package="cv_bridge"/>
  <depend package="opencv2"/>
  <depend package="pcl"/>
  <depend package="sensor_msgs"/>
<!-- <depend package="cv_bridge"/> -->

</package>


